audiobook_generator-1.0.8.dist-info/METADATA
audiobook_generator-1.0.8.dist-info/WHEEL
audiobook_generator-1.0.8.dist-info/entry_points.txt
audiobook_generator-1.0.8.dist-info/licenses/LICENSE
audiobook_generator/__init__.py
audiobook_generator/chapterizer.py
audiobook_generator/defaults.py
audiobook_generator/main.py
audiobook_generator/tts.py
audiobook_generator/util.py
audiobook_generator-1.0.8.dist-info/RECORD
