Metadata-Version: 2.1
Name: audiobook-generator
Version: 1.0.8
Summary: Generate audiobooks (mp3 files per chapter) from ebooks (currently only supports the epub format).
Project-URL: Homepage, https://github.com/houtianze/audiobook-generator
Project-URL: Repository, https://github.com/houtianze/audiobook-generator
Requires-Python: >=3.10
Requires-Dist: beautifulsoup4>=4.13.3
Requires-Dist: ebooklib>=0.18
Requires-Dist: kokoro>=0.8.2
Requires-Dist: misaki[en,zh]>=0.9.4
Requires-Dist: pip>=25.0.1
Requires-Dist: rich>=13.9.4
Requires-Dist: soundfile>=0.13.1
Requires-Dist: torch>=2.6.0
